LICENSE
README.md
setup.cfg
setup.py
pyngham/__init__.py
pyngham/extension.py
pyngham/pyngham.py
pyngham/rs.py
pyngham/spp.py
pyngham/version.py
pyngham.egg-info/PKG-INFO
pyngham.egg-info/SOURCES.txt
pyngham.egg-info/dependency_links.txt
pyngham.egg-info/requires.txt
pyngham.egg-info/top_level.txt