Metadata-Version: 2.1
Name: pyngham
Version: 1.1.1
Summary: PyNGHam library
Home-page: https://github.com/mgm8/pyngham
Download-URL: https://github.com/mgm8/pyngham/releases
Author: Gabriel Mariano Marcelino - PU5GMA
Author-email: gabriel.mm8@gmail.com
Maintainer: Gabriel Mariano Marcelino - PU5GMA
Maintainer-email: gabriel.mm8@gmail.com
License: LGPLv3
Platform: Linux
Platform: Windows
Platform: Solaris
Platform: Mac OS-X
Platform: Unix
Classifier: Development Status :: 5 - Production/Stable
Classifier: Environment :: Console
Classifier: Intended Audience :: Developers
Classifier: Intended Audience :: Education
Classifier: Intended Audience :: Science/Research
Classifier: Intended Audience :: Telecommunications Industry
Classifier: License :: OSI Approved :: GNU Lesser General Public License v3 (LGPLv3)
Classifier: Natural Language :: English
Classifier: Operating System :: OS Independent
Classifier: Programming Language :: Python :: 3
Classifier: Topic :: Communications :: Ham Radio
Classifier: Topic :: Education
Classifier: Topic :: Scientific/Engineering
Classifier: Topic :: Software Development :: Libraries
Classifier: Topic :: Software Development :: Libraries :: Python Modules
License-File: LICENSE
